{
 "submission_id": "15jx331",
 "title": "What show is the most quotable to you?",
 "selftext": "",
 "created_utc": 1691347376,
 "permalink": "/r/AskReddit/comments/15jx331/what_show_is_the_most_quotable_to_you/",
 "score": 157,
 "url": "https://www.reddit.com/r/AskReddit/comments/15jx331/what_show_is_the_most_quotable_to_you/",
 "comments": [
  {
   "comment_id": "jv28ms2",
   "message": "Simpsons.",
   "created_utc": 1691347412,
   "score": 29,
   "submission_id": "15jx331"
  },
  {
   "comment_id": "jv28z58",
   "message": "South Park",
   "created_utc": 1691347549,
   "score": 52,
   "submission_id": "15jx331"
  },
  {
   "comment_id": "jv2ba65",
   "message": "Seinfeld",
   "created_utc": 1691348490,
   "score": 212,
   "submission_id": "15jx331"
  },
  {
   "comment_id": "jv2bvre",
   "message": "The Office",
   "created_utc": 1691348737,
   "score": 253,
   "submission_id": "15jx331"
  },
  {
   "comment_id": "jv2bc97",
   "message": "Arrested Development",
   "created_utc": 1691348513,
   "score": 112,
   "submission_id": "15jx331"
  },
  {
   "comment_id": "jv2cid6",
   "message": "We quote Always Sunny all the time. \n\nI can't say trash anymore without saying it like Frank.",
   "created_utc": 1691348993,
   "score": 52,
   "submission_id": "15jx331"
  },
  {
   "comment_id": "jv2ikhw",
   "message": "Monty python... life of brian \"he's not the messiah, hes a very naughty boy\"... plus most of their other films too, cos its just a flesh wound.",
   "created_utc": 1691351485,
   "score": 67,
   "submission_id": "15jx331"
  },
  {
   "comment_id": "jv2fh4m",
   "message": "futurama",
   "created_utc": 1691350209,
   "score": 82,
   "submission_id": "15jx331"
  },
  {
   "comment_id": "jv2j15z",
   "message": "Buffy The Vampire Slayer",
   "created_utc": 1691351673,
   "score": 46,
   "submission_id": "15jx331"
  },
  {
   "comment_id": "jv28nn5",
   "message": "Letterkenny",
   "created_utc": 1691347421,
   "score": 83,
   "submission_id": "15jx331"
  },
  {
   "comment_id": "jv2b0di",
   "message": "\"B\", as in \"BUTTHOLE\", and \"M\", as in \"MANCY\"",
   "created_utc": 1691348377,
   "score": 79,
   "submission_id": "15jx331"
  },
  {
   "comment_id": "jv2i5w0",
   "message": "SpongeBob.",
   "created_utc": 1691351320,
   "score": 175,
   "submission_id": "15jx331"
  },
  {
   "comment_id": "jv2d8ek",
   "message": "Avatar the last airbender",
   "created_utc": 1691349288,
   "score": 6,
   "submission_id": "15jx331"
  },
  {
   "comment_id": "jv2i2ga",
   "message": "Peep show",
   "created_utc": 1691351281,
   "score": 34,
   "submission_id": "15jx331"
  },
  {
   "comment_id": "jv2lthn",
   "message": "Blackadder. I'm old. 😅",
   "created_utc": 1691352808,
   "score": 19,
   "submission_id": "15jx331"
  },
  {
   "comment_id": "jv29dws",
   "message": "Red Dwarf",
   "created_utc": 1691347715,
   "score": 13,
   "submission_id": "15jx331"
  },
  {
   "comment_id": "jv2bqtk",
   "message": "Sandor Clegane alone.",
   "created_utc": 1691348680,
   "score": 16,
   "submission_id": "15jx331"
  },
  {
   "comment_id": "jv2cmqw",
   "message": "Bojack horseman without the money.",
   "created_utc": 1691349043,
   "score": 22,
   "submission_id": "15jx331"
  },
  {
   "comment_id": "jv28qq4",
   "message": "House MD.",
   "created_utc": 1691347455,
   "score": 41,
   "submission_id": "15jx331"
  },
  {
   "comment_id": "jv2en6w",
   "message": "Always sunny",
   "created_utc": 1691349864,
   "score": 9,
   "submission_id": "15jx331"
  },
  {
   "comment_id": "jv2esf8",
   "message": "I Think You Should Leave",
   "created_utc": 1691349924,
   "score": 135,
   "submission_id": "15jx331"
  },
  {
   "comment_id": "jv2civb",
   "message": "Monty Python's Flying Circus",
   "created_utc": 1691348999,
   "score": 86,
   "submission_id": "15jx331"
  },
  {
   "comment_id": "jv2kk8s",
   "message": "Trailer Park Boys",
   "created_utc": 1691352296,
   "score": 42,
   "submission_id": "15jx331"
  },
  {
   "comment_id": "jv2mj0j",
   "message": "Blackadder",
   "created_utc": 1691353098,
   "score": 32,
   "submission_id": "15jx331"
  },
  {
   "comment_id": "jv2crll",
   "message": "Firefly, for a show with only 1 season.",
   "created_utc": 1691349097,
   "score": 19,
   "submission_id": "15jx331"
  },
  {
   "comment_id": "jv2ed1e",
   "message": "I’m an old fart, so it’s Gilmore Girls for me.",
   "created_utc": 1691349748,
   "score": 7,
   "submission_id": "15jx331"
  },
  {
   "comment_id": "jv2g5j6",
   "message": "Seinfeld",
   "created_utc": 1691350496,
   "score": 12,
   "submission_id": "15jx331"
  },
  {
   "comment_id": "jv2j384",
   "message": "Community is streets ahead.",
   "created_utc": 1691351696,
   "score": 126,
   "submission_id": "15jx331"
  },
  {
   "comment_id": "jv28wdy",
   "message": "Always sunny",
   "created_utc": 1691347518,
   "score": 2,
   "submission_id": "15jx331"
  },
  {
   "comment_id": "jv2ddex",
   "message": "Babylon 5",
   "created_utc": 1691349345,
   "score": 2,
   "submission_id": "15jx331"
  },
  {
   "comment_id": "jv2jnyc",
   "message": "Sunny (IASIP)",
   "created_utc": 1691351931,
   "score": 1,
   "submission_id": "15jx331"
  },
  {
   "comment_id": "jv2jw5b",
   "message": "Parks and Rec.",
   "created_utc": 1691352024,
   "score": 155,
   "submission_id": "15jx331"
  },
  {
   "comment_id": "jv2kbmf",
   "message": "I Think You Should Leave, and It's Always Sunny In Philadelphia are about equal in my book",
   "created_utc": 1691352199,
   "score": 1,
   "submission_id": "15jx331"
  },
  {
   "comment_id": "jv2bdko",
   "message": "Prolly a less popular opinion, but Breaking Bad",
   "created_utc": 1691348528,
   "score": 1,
   "submission_id": "15jx331"
  },
  {
   "comment_id": "jv2c7xn",
   "message": "Archer. Futurama. Simpsons.",
   "created_utc": 1691348872,
   "score": 1,
   "submission_id": "15jx331"
  },
  {
   "comment_id": "jv2gj3r",
   "message": "The Office",
   "created_utc": 1691350651,
   "score": 1,
   "submission_id": "15jx331"
  },
  {
   "comment_id": "jv2ccb6",
   "message": "Gossip girl",
   "created_utc": 1691348923,
   "score": 1,
   "submission_id": "15jx331"
  },
  {
   "comment_id": "jv2d04b",
   "message": "Definitely GoT. Bunch of nobles fighting for power is definitely full of iconic lines.",
   "created_utc": 1691349194,
   "score": 1,
   "submission_id": "15jx331"
  },
  {
   "comment_id": "jv2deq2",
   "message": "The Thick Of It, if only for the ample swearing.",
   "created_utc": 1691349360,
   "score": 1,
   "submission_id": "15jx331"
  },
  {
   "comment_id": "jv2e3ub",
   "message": "Police Squad. ‘Like a blind person at an orgy, I had to feel things out.’",
   "created_utc": 1691349644,
   "score": 1,
   "submission_id": "15jx331"
  },
  {
   "comment_id": "jv2glsv",
   "message": "The Big Bang Theory is definitely the one I quote the most in everyday life",
   "created_utc": 1691350681,
   "score": 9,
   "submission_id": "15jx331"
  },
  {
   "comment_id": "jv2i5bp",
   "message": "King of the Hill for sure",
   "created_utc": 1691351314,
   "score": 1,
   "submission_id": "15jx331"
  },
  {
   "comment_id": "jv2ja3n",
   "message": "The office \u0026amp; Arrested Development",
   "created_utc": 1691351773,
   "score": 1,
   "submission_id": "15jx331"
  },
  {
   "comment_id": "jv2jomu",
   "message": "The Emperor's New Groove. Wife and I quote it daily.",
   "created_utc": 1691351939,
   "score": 7,
   "submission_id": "15jx331"
  },
  {
   "comment_id": "jv2jxkb",
   "message": "brooklyn 99",
   "created_utc": 1691352040,
   "score": 127,
   "submission_id": "15jx331"
  },
  {
   "comment_id": "jv2kq55",
   "message": "Friends",
   "created_utc": 1691352363,
   "score": 1,
   "submission_id": "15jx331"
  },
  {
   "comment_id": "jv2kwx4",
   "message": "If you don’t know, you’re streets behind.",
   "created_utc": 1691352439,
   "score": 1,
   "submission_id": "15jx331"
  },
  {
   "comment_id": "jv2kzfj",
   "message": "Community",
   "created_utc": 1691352468,
   "score": 1,
   "submission_id": "15jx331"
  },
  {
   "comment_id": "jv2laqm",
   "message": "New Girl",
   "created_utc": 1691352596,
   "score": 1,
   "submission_id": "15jx331"
  },
  {
   "comment_id": "jv2lcoa",
   "message": "Friends",
   "created_utc": 1691352619,
   "score": 31,
   "submission_id": "15jx331"
  },
  {
   "comment_id": "jv2lnao",
   "message": "American dad",
   "created_utc": 1691352739,
   "score": 1,
   "submission_id": "15jx331"
  },
  {
   "comment_id": "jv2h97v",
   "message": "The Office.",
   "created_utc": 1691350952,
   "score": 1,
   "submission_id": "15jx331"
  },
  {
   "comment_id": "jv2bz8o",
   "message": "Super troopers",
   "created_utc": 1691348775,
   "score": 0,
   "submission_id": "15jx331"
  },
  {
   "comment_id": "jv2d53c",
   "message": "Sopranos or family guy or friends or scrubs",
   "created_utc": 1691349250,
   "score": 0,
   "submission_id": "15jx331"
  },
  {
   "comment_id": "jv2dh6o",
   "message": "The office because sometimes I’ll start a sentence and I don’t even know where it’s going. I just hope I find it along the way.",
   "created_utc": 1691349388,
   "score": 0,
   "submission_id": "15jx331"
  },
  {
   "comment_id": "jv2j0z6",
   "message": "Identity theft is not a joke, Jim",
   "created_utc": 1691351671,
   "score": 1,
   "submission_id": "15jx331"
  },
  {
   "comment_id": "jv2c4pz",
   "message": "There were a lot of funny lines from the Office tv show.",
   "created_utc": 1691348837,
   "score": 255,
   "submission_id": "15jx331"
  },
  {
   "comment_id": "jv29dad",
   "message": "nice",
   "created_utc": 1691347708,
   "score": 0,
   "submission_id": "15jx331"
  },
  {
   "comment_id": "jv2b5dx",
   "message": "",
   "created_utc": 0,
   "score": 0,
   "submission_id": "15jx331"
  },
  {
   "comment_id": "jv2bjf1",
   "message": "MASH",
   "created_utc": 1691348595,
   "score": 0,
   "submission_id": "15jx331"
  },
  {
   "comment_id": "jv2bwai",
   "message": "Kaamelott",
   "created_utc": 1691348743,
   "score": 0,
   "submission_id": "15jx331"
  },
  {
   "comment_id": "jv2es1i",
   "message": "Spongebob squarepants",
   "created_utc": 1691349919,
   "score": 0,
   "submission_id": "15jx331"
  },
  {
   "comment_id": "jv2f9e8",
   "message": "The original Batman.\n\n\"Holy [something]!\" (Burt Ward got a star on the Hollywood Walk of Fame for this.)",
   "created_utc": 1691350120,
   "score": 0,
   "submission_id": "15jx331"
  },
  {
   "comment_id": "jv2fbem",
   "message": "SAY MY NAME",
   "created_utc": 1691350143,
   "score": 0,
   "submission_id": "15jx331"
  },
  {
   "comment_id": "jv2fgsd",
   "message": "If internet cartoons count, Homestar Runner.",
   "created_utc": 1691350205,
   "score": 0,
   "submission_id": "15jx331"
  },
  {
   "comment_id": "jv2fsbw",
   "message": "LOTR",
   "created_utc": 1691350341,
   "score": 0,
   "submission_id": "15jx331"
  },
  {
   "comment_id": "jv2fxfm",
   "message": "Firefly, Castle, Simpsons, South Park",
   "created_utc": 1691350401,
   "score": 0,
   "submission_id": "15jx331"
  },
  {
   "comment_id": "jv2gv6p",
   "message": "The Simpsons.  D’oh!",
   "created_utc": 1691350791,
   "score": 1,
   "submission_id": "15jx331"
  },
  {
   "comment_id": "jv2gvko",
   "message": "Arrested Development",
   "created_utc": 1691350796,
   "score": 1,
   "submission_id": "15jx331"
  },
  {
   "comment_id": "jv2ibr6",
   "message": "Sopranos or Always Sunny 🌴",
   "created_utc": 1691351385,
   "score": 1,
   "submission_id": "15jx331"
  },
  {
   "comment_id": "jv2ibzh",
   "message": "Fargo",
   "created_utc": 1691351388,
   "score": 1,
   "submission_id": "15jx331"
  },
  {
   "comment_id": "jv2iesr",
   "message": "Gotham",
   "created_utc": 1691351420,
   "score": 1,
   "submission_id": "15jx331"
  },
  {
   "comment_id": "jv2iudr",
   "message": "South Park or Its Always sunny",
   "created_utc": 1691351595,
   "score": 1,
   "submission_id": "15jx331"
  },
  {
   "comment_id": "jv2ivea",
   "message": "As someone with most of my family in Philadelphia, The Sopranos. The antics of the characters are so true. Kills me. “Yea howya doin” “mootsadell cheese” “manigot”. On top of the not so politically correct things, “I loved that cocksucker like a brother” “AYEE FUCK OUTTA HEA”",
   "created_utc": 1691351607,
   "score": 1,
   "submission_id": "15jx331"
  },
  {
   "comment_id": "jv2epek",
   "message": "Forrest Gump",
   "created_utc": 1691349890,
   "score": 255,
   "submission_id": "15jx331"
  },
  {
   "comment_id": "jv2e9t5",
   "message": "QI",
   "created_utc": 1691349711,
   "score": 1,
   "submission_id": "15jx331"
  },
  {
   "comment_id": "jv2g75e",
   "message": "South park, parks \u0026amp; rec, the it crowd",
   "created_utc": 1691350514,
   "score": 1,
   "submission_id": "15jx331"
  },
  {
   "comment_id": "jv2j0zp",
   "message": "Mystery Science Theater 3K and Rifftrax",
   "created_utc": 1691351671,
   "score": 1,
   "submission_id": "15jx331"
  },
  {
   "comment_id": "jv2j4j6",
   "message": "SpongeBob",
   "created_utc": 1691351710,
   "score": 1,
   "submission_id": "15jx331"
  },
  {
   "comment_id": "jv2j6yq",
   "message": "Simpsons!",
   "created_utc": 1691351738,
   "score": 1,
   "submission_id": "15jx331"
  },
  {
   "comment_id": "jv2jfxz",
   "message": "MST3K.\n\n\u0026amp;#x200B;\n\nBecause not only do you get quotable from the riffers, you also get them from the movies/shorts they watch.",
   "created_utc": 1691351840,
   "score": 8,
   "submission_id": "15jx331"
  },
  {
   "comment_id": "jv2jg8l",
   "message": "The Sopranos.  Sharp as a fuckin' cue ball, this one!",
   "created_utc": 1691351843,
   "score": 1,
   "submission_id": "15jx331"
  },
  {
   "comment_id": "jv2jn6l",
   "message": "Either the Simpsons or 30 Rock.",
   "created_utc": 1691351923,
   "score": 1,
   "submission_id": "15jx331"
  },
  {
   "comment_id": "jv2jomw",
   "message": "Blazing Saddles",
   "created_utc": 1691351939,
   "score": 1,
   "submission_id": "15jx331"
  },
  {
   "comment_id": "jv2jpbu",
   "message": "The Thick of It",
   "created_utc": 1691351946,
   "score": 1,
   "submission_id": "15jx331"
  },
  {
   "comment_id": "jv2jr8l",
   "message": "I don’t need your cherry trees Julian.",
   "created_utc": 1691351969,
   "score": 1,
   "submission_id": "15jx331"
  },
  {
   "comment_id": "jv2jzdg",
   "message": "Anything Marvel",
   "created_utc": 1691352061,
   "score": 1,
   "submission_id": "15jx331"
  },
  {
   "comment_id": "jv2k0ob",
   "message": "The Office for general statements, Doctor Who for jokes that are a bit more niche.",
   "created_utc": 1691352076,
   "score": 1,
   "submission_id": "15jx331"
  },
  {
   "comment_id": "jv2k1jf",
   "message": "Bojack horseman but mostly the office mainly Michael Scott",
   "created_utc": 1691352086,
   "score": 1,
   "submission_id": "15jx331"
  },
  {
   "comment_id": "jv2k3db",
   "message": "Based upon friends it is the Simpsons. I pretend I know their references...",
   "created_utc": 1691352106,
   "score": 3,
   "submission_id": "15jx331"
  },
  {
   "comment_id": "jv2k3wn",
   "message": "SpongeBob all the way",
   "created_utc": 1691352112,
   "score": 1,
   "submission_id": "15jx331"
  },
  {
   "comment_id": "jv2kfny",
   "message": "Peep show",
   "created_utc": 1691352246,
   "score": 1,
   "submission_id": "15jx331"
  },
  {
   "comment_id": "jv2kgjv",
   "message": "Succession has some gold.",
   "created_utc": 1691352256,
   "score": 1,
   "submission_id": "15jx331"
  },
  {
   "comment_id": "jv2kgku",
   "message": "Euphoria has quite a few lines that made it into my daily vocabulary 😅",
   "created_utc": 1691352256,
   "score": 1,
   "submission_id": "15jx331"
  },
  {
   "comment_id": "jv2kjqv",
   "message": "Breaking Bad",
   "created_utc": 1691352290,
   "score": 1,
   "submission_id": "15jx331"
  },
  {
   "comment_id": "jv2kjxz",
   "message": "Martin",
   "created_utc": 1691352292,
   "score": 1,
   "submission_id": "15jx331"
  },
  {
   "comment_id": "jv2kllq",
   "message": "SpongeBob. The office.",
   "created_utc": 1691352311,
   "score": 1,
   "submission_id": "15jx331"
  },
  {
   "comment_id": "jv2km9n",
   "message": "Sopranos",
   "created_utc": 1691352319,
   "score": 1,
   "submission_id": "15jx331"
  },
  {
   "comment_id": "jv2ktye",
   "message": "The Big Lebowski",
   "created_utc": 1691352406,
   "score": 1,
   "submission_id": "15jx331"
  },
  {
   "comment_id": "jv2kvmr",
   "message": "Santa Claus loves to spread Christmas cheer. His sack is so big 'cause he comes once a year. His sack is so full that it drags on the ground. He has a surprise for every kid in town. Santa comes down the chimney, fills stockings with his load. Gives the kids a white Christmas, it looks like it snowed. While the kids sleep he leaves them a special surprise. When they wake up they can't believe their eyes. It's all over their room, in their bed, on the floor. Candies and treats, presents galore. Children love his balls and toys that he brings. He empties his sack all over their things. He'll soon be visiting every kid around. 'Cause Santa Claus is coming to town.",
   "created_utc": 1691352425,
   "score": 1,
   "submission_id": "15jx331"
  },
  {
   "comment_id": "jv2l07g",
   "message": "Ted Lasso",
   "created_utc": 1691352476,
   "score": 1,
   "submission_id": "15jx331"
  },
  {
   "comment_id": "jv2l244",
   "message": "Seinfeld",
   "created_utc": 1691352497,
   "score": 3,
   "submission_id": "15jx331"
  },
  {
   "comment_id": "jv2l285",
   "message": "Toss up between The Simpsons \u0026amp; What We Do In The Shadows for me.",
   "created_utc": 1691352499,
   "score": 1,
   "submission_id": "15jx331"
  },
  {
   "comment_id": "jv2lhax",
   "message": "Always Sunny\nAmerican Dad\n\nI quote both of them multiple times a day",
   "created_utc": 1691352671,
   "score": 1,
   "submission_id": "15jx331"
  },
  {
   "comment_id": "jv2ljof",
   "message": "Shrek",
   "created_utc": 1691352697,
   "score": 1,
   "submission_id": "15jx331"
  },
  {
   "comment_id": "jv2lo9p",
   "message": "The Office",
   "created_utc": 1691352750,
   "score": 1,
   "submission_id": "15jx331"
  },
  {
   "comment_id": "jv2lqoz",
   "message": "Futurama!",
   "created_utc": 1691352777,
   "score": 1,
   "submission_id": "15jx331"
  },
  {
   "comment_id": "jv2lqtv",
   "message": "I Think You Should Leave",
   "created_utc": 1691352778,
   "score": 1,
   "submission_id": "15jx331"
  },
  {
   "comment_id": "jv2lrp1",
   "message": "Seinfeld",
   "created_utc": 1691352788,
   "score": 3,
   "submission_id": "15jx331"
  },
  {
   "comment_id": "jv2m6p7",
   "message": "D'oh! The Simpsons... they've been quotable since before it was cool!",
   "created_utc": 1691352958,
   "score": 1,
   "submission_id": "15jx331"
  },
  {
   "comment_id": "jv2m7a5",
   "message": "Classic Simpsons. Pre season 11.",
   "created_utc": 1691352965,
   "score": 1,
   "submission_id": "15jx331"
  },
  {
   "comment_id": "jv2m8td",
   "message": "Idiocracy",
   "created_utc": 1691352982,
   "score": 1,
   "submission_id": "15jx331"
  },
  {
   "comment_id": "jv2mmdq",
   "message": "SpongeBob",
   "created_utc": 1691353138,
   "score": 1,
   "submission_id": "15jx331"
  },
  {
   "comment_id": "jv2mpsi",
   "message": "Spongebob",
   "created_utc": 1691353176,
   "score": 1,
   "submission_id": "15jx331"
  },
  {
   "comment_id": "jv2mrhz",
   "message": "Everything Ron Swanson from Parks and Rec.",
   "created_utc": 1691353195,
   "score": 1,
   "submission_id": "15jx331"
  },
  {
   "comment_id": "jv2msgl",
   "message": "Monty Python's Flying Circus.\n\n\u0026amp;#x200B;\n\n\"And now, a man with three buttocks.\"",
   "created_utc": 1691353206,
   "score": 1,
   "submission_id": "15jx331"
  },
  {
   "comment_id": "jv2mvsr",
   "message": "I’m in rehab so bojack horseman",
   "created_utc": 1691353243,
   "score": 1,
   "submission_id": "15jx331"
  },
  {
   "comment_id": "jv2n3rg",
   "message": "Futurama. I quote it almost every day.",
   "created_utc": 1691353332,
   "score": 1,
   "submission_id": "15jx331"
  },
  {
   "comment_id": "jv2n9tr",
   "message": "Doctor Who",
   "created_utc": 1691353402,
   "score": 1,
   "submission_id": "15jx331"
  },
  {
   "comment_id": "jv2ncsj",
   "message": "Forrest Gump",
   "created_utc": 1691353436,
   "score": 1,
   "submission_id": "15jx331"
  },
  {
   "comment_id": "jv2ndsn",
   "message": "M*A*S*H\n(Sue me I'm old lol)",
   "created_utc": 1691353448,
   "score": 1,
   "submission_id": "15jx331"
  },
  {
   "comment_id": "jv2ne1x",
   "message": "The Office",
   "created_utc": 1691353451,
   "score": 3,
   "submission_id": "15jx331"
  },
  {
   "comment_id": "jv2nkwh",
   "message": "Key \u0026amp; Peele",
   "created_utc": 1691353529,
   "score": 1,
   "submission_id": "15jx331"
  },
  {
   "comment_id": "jv2nmym",
   "message": "Peep Show",
   "created_utc": 1691353552,
   "score": 1,
   "submission_id": "15jx331"
  },
  {
   "comment_id": "jv2nn4c",
   "message": "The Flash. Cue u/TheWinterFox5lol quoting it now.",
   "created_utc": 1691353554,
   "score": 1,
   "submission_id": "15jx331"
  },
  {
   "comment_id": "jv2nqzo",
   "message": "Derek",
   "created_utc": 1691353598,
   "score": 1,
   "submission_id": "15jx331"
  },
  {
   "comment_id": "jv2nqzw",
   "message": "The office. I watched the whole thing because I was living in a motel with a dvd player and the wi-fi sucked. So a coworker let me borrow it, it was pretty hilarious, but a lot of the show was just meh. But a lot of great quotes came from it.",
   "created_utc": 1691353598,
   "score": 1,
   "submission_id": "15jx331"
  },
  {
   "comment_id": "jv2nrcc",
   "message": "King of the Hill",
   "created_utc": 1691353602,
   "score": 1,
   "submission_id": "15jx331"
  },
  {
   "comment_id": "jv2ntd3",
   "message": "Scrubs. Especially Dr Cox.",
   "created_utc": 1691353625,
   "score": 40,
   "submission_id": "15jx331"
  },
  {
   "comment_id": "jv2ntft",
   "message": "Breaking Bad…so many one liners like “I am the one who knocks” that are really funny out of context",
   "created_utc": 1691353626,
   "score": 1,
   "submission_id": "15jx331"
  },
  {
   "comment_id": "jv2nwbh",
   "message": "HIMYM",
   "created_utc": 1691353658,
   "score": 1,
   "submission_id": "15jx331"
  },
  {
   "comment_id": "jv2nz4q",
   "message": "“Pudding!” Iykyk😂😂",
   "created_utc": 1691353690,
   "score": 1,
   "submission_id": "15jx331"
  },
  {
   "comment_id": "jv2o0ao",
   "message": "Family guy",
   "created_utc": 1691353702,
   "score": 1,
   "submission_id": "15jx331"
  },
  {
   "comment_id": "jv2o0xg",
   "message": "\"I think we all need to consider the other possibilities\"",
   "created_utc": 1691353710,
   "score": 1,
   "submission_id": "15jx331"
  },
  {
   "comment_id": "jv2o2ex",
   "message": "Sons of Anarchy",
   "created_utc": 1691353727,
   "score": 1,
   "submission_id": "15jx331"
  },
  {
   "comment_id": "jv2o3sf",
   "message": "Parks and recreation, especially Ron Swanson's quotes !",
   "created_utc": 1691353742,
   "score": 1,
   "submission_id": "15jx331"
  },
  {
   "comment_id": "jv2o59x",
   "message": "The Office",
   "created_utc": 1691353759,
   "score": 1,
   "submission_id": "15jx331"
  },
  {
   "comment_id": "jv2o640",
   "message": "Family Feud",
   "created_utc": 1691353769,
   "score": 1,
   "submission_id": "15jx331"
  },
  {
   "comment_id": "jv2oaji",
   "message": "Old school Simpson’s or King of the Hill.",
   "created_utc": 1691353819,
   "score": 1,
   "submission_id": "15jx331"
  },
  {
   "comment_id": "jv2oee5",
   "message": "Have not seen Peep Show yet.\n\n\"People like Coldplay and voted for the Nazis, you can’t trust people.\"\n\n\"Look at me, friends with a big black businessman, like it’s the most natural thing in the world.\"\n\n\"I bet she even does nice poos, little Maltesers that smell like The Body Shop.\"",
   "created_utc": 1691353863,
   "score": 1,
   "submission_id": "15jx331"
  },
  {
   "comment_id": "jv2oee8",
   "message": "Brooklyn 99",
   "created_utc": 1691353863,
   "score": 1,
   "submission_id": "15jx331"
  },
  {
   "comment_id": "jv2ofml",
   "message": "[removed]",
   "created_utc": 1691353877,
   "score": 39,
   "submission_id": "15jx331"
  },
  {
   "comment_id": "jv2ofvt",
   "message": "The Office (uk)",
   "created_utc": 1691353880,
   "score": 1,
   "submission_id": "15jx331"
  },
  {
   "comment_id": "jv2oklw",
   "message": "Sopranos",
   "created_utc": 1691353933,
   "score": 4,
   "submission_id": "15jx331"
  },
  {
   "comment_id": "jv2olsh",
   "message": "SpongeBob 100 percent. \n\nEspecially seasons 1 through 3 up to the movie. In my opinion thats where the show ends.",
   "created_utc": 1691353946,
   "score": 1,
   "submission_id": "15jx331"
  },
  {
   "comment_id": "jv2on7w",
   "message": "Adventure time!",
   "created_utc": 1691353962,
   "score": 1,
   "submission_id": "15jx331"
  },
  {
   "comment_id": "jv2onzq",
   "message": "Seinfeld.",
   "created_utc": 1691353971,
   "score": 3,
   "submission_id": "15jx331"
  },
  {
   "comment_id": "jv2oo88",
   "message": "It’s always sunny in Philadelphia",
   "created_utc": 1691353974,
   "score": 1,
   "submission_id": "15jx331"
  },
  {
   "comment_id": "jv2oree",
   "message": "It’s always sunny is more better than the rest",
   "created_utc": 1691354009,
   "score": 1,
   "submission_id": "15jx331"
  },
  {
   "comment_id": "jv2oroj",
   "message": "\"Smokes, let's go!\"",
   "created_utc": 1691354012,
   "score": 1,
   "submission_id": "15jx331"
  },
  {
   "comment_id": "jv2oroo",
   "message": "RuPaul’s Drag Race\n\n90% of gay men of know what you’re talking about when you reference Drag Race (I would know, I am one)",
   "created_utc": 1691354012,
   "score": 19,
   "submission_id": "15jx331"
  },
  {
   "comment_id": "jv2osc3",
   "message": "Its Always Sunny In Philadelphia",
   "created_utc": 1691354020,
   "score": 1,
   "submission_id": "15jx331"
  },
  {
   "comment_id": "jv2osm0",
   "message": "SpongeBob",
   "created_utc": 1691354023,
   "score": 1,
   "submission_id": "15jx331"
  },
  {
   "comment_id": "jv2ovwf",
   "message": "YFMTS",
   "created_utc": 1691354060,
   "score": 1,
   "submission_id": "15jx331"
  },
  {
   "comment_id": "jv2oy3t",
   "message": "Brooklyn Nine-Nine\n\nMy favorite example:\n\"My mother cried the day I was born because she knew she would never be better than me.\"",
   "created_utc": 1691354085,
   "score": 1,
   "submission_id": "15jx331"
  },
  {
   "comment_id": "jv2ozbb",
   "message": "For me it's Predator, with Alien a very close second.",
   "created_utc": 1691354099,
   "score": 1,
   "submission_id": "15jx331"
  },
  {
   "comment_id": "jv2wlft",
   "message": "How I Met Your Mother for me.\n\nI mean some episodes were even centered around quotes.\n\nLawyered, nothing good happens after 2 am, suit up, legen.. wait for it.. dary etc. I feel like I could go on forever lol.",
   "created_utc": 1691357214,
   "score": 168,
   "submission_id": "15jx331"
  },
  {
   "comment_id": "jv2q6lc",
   "message": "Chapelle Show. \n\nI’m rich bitch.  What!  Cocaine is a hell of a drug.  Is Wayne Brady gonna have to choke a bitch?",
   "created_utc": 1691354586,
   "score": 92,
   "submission_id": "15jx331"
  },
  {
   "comment_id": "jv2qkfi",
   "message": "The Sopranos",
   "created_utc": 1691354744,
   "score": 44,
   "submission_id": "15jx331"
  },
  {
   "comment_id": "jv2qrvn",
   "message": "The sopranos",
   "created_utc": 1691354827,
   "score": 6,
   "submission_id": "15jx331"
  },
  {
   "comment_id": "jv2td6x",
   "message": "Community",
   "created_utc": 1691355878,
   "score": 134,
   "submission_id": "15jx331"
  },
  {
   "comment_id": "jv2yirr",
   "message": "Schitts Creek",
   "created_utc": 1691358044,
   "score": 13,
   "submission_id": "15jx331"
  },
  {
   "comment_id": "jv2p9l1",
   "message": "The Simpsons \u0026amp; Seinfeld",
   "created_utc": 1691354215,
   "score": 4,
   "submission_id": "15jx331"
  },
  {
   "comment_id": "jv2rxxy",
   "message": "Black Adder",
   "created_utc": 1691355301,
   "score": 5,
   "submission_id": "15jx331"
  },
  {
   "comment_id": "jv2sx3d",
   "message": "Sopranos",
   "created_utc": 1691355696,
   "score": 6,
   "submission_id": "15jx331"
  },
  {
   "comment_id": "jv2u0wa",
   "message": "Psych",
   "created_utc": 1691356145,
   "score": 50,
   "submission_id": "15jx331"
  },
  {
   "comment_id": "jv2q5qx",
   "message": "Seinfeld",
   "created_utc": 1691354577,
   "score": 3,
   "submission_id": "15jx331"
  },
  {
   "comment_id": "jv2s0t8",
   "message": "South Park, Schitts creek",
   "created_utc": 1691355333,
   "score": 3,
   "submission_id": "15jx331"
  },
  {
   "comment_id": "jv2s8ym",
   "message": "Malcolm in the middle.\n\n\"Dad I can't die, I'm 17\" so just because you're 17 you can't die?\n\n\"Frankly I just don't see it happening.\"",
   "created_utc": 1691355426,
   "score": 24,
   "submission_id": "15jx331"
  },
  {
   "comment_id": "jv2sq1t",
   "message": "Seinfeld. \n\n“Marriage? Family? They’re prisons! Manmade prisons! You’re doing time!” Kramer",
   "created_utc": 1691355618,
   "score": 3,
   "submission_id": "15jx331"
  },
  {
   "comment_id": "jv2tdni",
   "message": "Seinfeld",
   "created_utc": 1691355883,
   "score": 3,
   "submission_id": "15jx331"
  },
  {
   "comment_id": "jv2tm6w",
   "message": "Psych",
   "created_utc": 1691355978,
   "score": 7,
   "submission_id": "15jx331"
  },
  {
   "comment_id": "jv2xtto",
   "message": "Seinfeld… hands down. I work with younger folks who have no idea what I’m referencing 😂😂",
   "created_utc": 1691357743,
   "score": 1,
   "submission_id": "15jx331"
  },
  {
   "comment_id": "jv30m4p",
   "message": "The IT Crowd",
   "created_utc": 1691358949,
   "score": 57,
   "submission_id": "15jx331"
  },
  {
   "comment_id": "jv34t3i",
   "message": "Could I BE any more quotable?",
   "created_utc": 1691360805,
   "score": 43,
   "submission_id": "15jx331"
  },
  {
   "comment_id": "jv33pfb",
   "message": "",
   "created_utc": 0,
   "score": 0,
   "submission_id": "15jx331"
  },
  {
   "comment_id": "jv2zx29",
   "message": "",
   "created_utc": 0,
   "score": 0,
   "submission_id": "15jx331"
  },
  {
   "comment_id": "jv34amq",
   "message": "",
   "created_utc": 0,
   "score": 0,
   "submission_id": "15jx331"
  }
 ]
}