{
 "submission_id": "15yn96i",
 "title": "What food is so addictive that you consider it too dangerous to keep on hand?",
 "selftext": "",
 "created_utc": 1692749038,
 "permalink": "/r/AskReddit/comments/15yn96i/what_food_is_so_addictive_that_you_consider_it/",
 "score": 181,
 "url": "https://www.reddit.com/r/AskReddit/comments/15yn96i/what_food_is_so_addictive_that_you_consider_it/",
 "comments": [
  {
   "comment_id": "jxcmwrd",
   "message": "Pizza",
   "created_utc": 1692751805,
   "score": 10,
   "submission_id": "15yn96i"
  },
  {
   "comment_id": "jxctob7",
   "message": "Any freshly baked goods - cake, cookies, cinnamon rolls, banana bread, donuts..",
   "created_utc": 1692754767,
   "score": 190,
   "submission_id": "15yn96i"
  },
  {
   "comment_id": "jxcha08",
   "message": "Chips",
   "created_utc": 1692749388,
   "score": 162,
   "submission_id": "15yn96i"
  },
  {
   "comment_id": "jxcnwlm",
   "message": "Smartfood White Cheddar Popcorn. I could eat a family size bag in one sitting.",
   "created_utc": 1692752233,
   "score": 194,
   "submission_id": "15yn96i"
  },
  {
   "comment_id": "jxcmc60",
   "message": "Ice cream, any type. If I buy a tub, it's gone in a few minutes... Zero self control.",
   "created_utc": 1692751558,
   "score": 12,
   "submission_id": "15yn96i"
  },
  {
   "comment_id": "jxcnnbu",
   "message": "Anything made by the fine people over at Reese’s",
   "created_utc": 1692752121,
   "score": 213,
   "submission_id": "15yn96i"
  },
  {
   "comment_id": "jxcjt0w",
   "message": "I'm not to be trusted with Lindor Truffles.",
   "created_utc": 1692750469,
   "score": 213,
   "submission_id": "15yn96i"
  },
  {
   "comment_id": "jxcmcox",
   "message": "Snyders of Hanover pretzel bites. The honey mustard and onion flavor. They’re so damn good but start to hurt my mouth after a while. Kinda like sour patch kids.",
   "created_utc": 1692751565,
   "score": 199,
   "submission_id": "15yn96i"
  },
  {
   "comment_id": "jxcuz0a",
   "message": "Goldfish. They never see sunrise in this house.",
   "created_utc": 1692755348,
   "score": 98,
   "submission_id": "15yn96i"
  },
  {
   "comment_id": "jxcifw6",
   "message": "Doritos",
   "created_utc": 1692749891,
   "score": 164,
   "submission_id": "15yn96i"
  },
  {
   "comment_id": "jxcor3h",
   "message": "Kettle chips. Anything savory or salty snack lol",
   "created_utc": 1692752602,
   "score": 81,
   "submission_id": "15yn96i"
  },
  {
   "comment_id": "jxcnd3e",
   "message": "Brownies",
   "created_utc": 1692751999,
   "score": 177,
   "submission_id": "15yn96i"
  },
  {
   "comment_id": "jxcqrwg",
   "message": "Peanut butter m\u0026amp;ms",
   "created_utc": 1692753488,
   "score": 170,
   "submission_id": "15yn96i"
  },
  {
   "comment_id": "jxcqxnj",
   "message": "Cheesecake. It has a short fridge life... I better eat it all now just in case!",
   "created_utc": 1692753558,
   "score": 16,
   "submission_id": "15yn96i"
  },
  {
   "comment_id": "jxcpjxj",
   "message": "Chicken and a biscuit crackers",
   "created_utc": 1692752951,
   "score": 31,
   "submission_id": "15yn96i"
  },
  {
   "comment_id": "jxcp5ud",
   "message": "Peanut m\u0026amp;ms.",
   "created_utc": 1692752779,
   "score": 45,
   "submission_id": "15yn96i"
  },
  {
   "comment_id": "jxcorgs",
   "message": "Ice cream. Specifically Häagen-Dazs honey salted caramel almond ice cream.",
   "created_utc": 1692752607,
   "score": 92,
   "submission_id": "15yn96i"
  },
  {
   "comment_id": "jxcgk9q",
   "message": "Oreos",
   "created_utc": 1692749077,
   "score": 125,
   "submission_id": "15yn96i"
  },
  {
   "comment_id": "jxcn1an",
   "message": "Pistachios.",
   "created_utc": 1692751859,
   "score": 81,
   "submission_id": "15yn96i"
  },
  {
   "comment_id": "jxcii5o",
   "message": "Cheeze-its! The extra toasty kind.",
   "created_utc": 1692749919,
   "score": 67,
   "submission_id": "15yn96i"
  },
  {
   "comment_id": "jxcrrox",
   "message": "Tiramisu",
   "created_utc": 1692753922,
   "score": 70,
   "submission_id": "15yn96i"
  },
  {
   "comment_id": "jxcvfc7",
   "message": "Claussen pickles.  \n\n\nAll the pickles, the juice, gone....3 days tops.  \n\n\nJust....gimmie the jar. Don't look at me.",
   "created_utc": 1692755550,
   "score": 66,
   "submission_id": "15yn96i"
  },
  {
   "comment_id": "jxcrhvs",
   "message": "Pringles (original)",
   "created_utc": 1692753801,
   "score": 37,
   "submission_id": "15yn96i"
  },
  {
   "comment_id": "jxcxqkj",
   "message": "Cinnamon Toast Crunch. I eat low carb. Have been for more than a decade. Doesn’t faze me. But I will fuck up some CTC.",
   "created_utc": 1692756586,
   "score": 31,
   "submission_id": "15yn96i"
  },
  {
   "comment_id": "jxcydmd",
   "message": "Little Debbie Nutty Buddy’s. I will eat the whole box.",
   "created_utc": 1692756877,
   "score": 32,
   "submission_id": "15yn96i"
  },
  {
   "comment_id": "jxco5ua",
   "message": "Donuts",
   "created_utc": 1692752345,
   "score": 78,
   "submission_id": "15yn96i"
  },
  {
   "comment_id": "jxcko53",
   "message": "Cake",
   "created_utc": 1692750841,
   "score": 58,
   "submission_id": "15yn96i"
  },
  {
   "comment_id": "jxcpmti",
   "message": "Extra crunchy peanut butter.\n\nI ate one of the BIG ones from Walmart in 3 days.  Realized I don't have the self control to keep that stuff in the house anymore 😔",
   "created_utc": 1692752986,
   "score": 28,
   "submission_id": "15yn96i"
  },
  {
   "comment_id": "jxd0wrg",
   "message": "dot's pretzels. dot must have put CRACK in her pretzels because i cannot stop once i start",
   "created_utc": 1692758041,
   "score": 28,
   "submission_id": "15yn96i"
  },
  {
   "comment_id": "jxcrizs",
   "message": "Sour Patch Kids. If I buy a 1 lb bag, I eat it in like 3 days tops. It's *bad*, so I don't buy them but every few months. That's such a humongous amount of empty calories.",
   "created_utc": 1692753815,
   "score": 50,
   "submission_id": "15yn96i"
  },
  {
   "comment_id": "jxctkie",
   "message": "The French vanilla Pirouette cookies from Pepperidge Farms. I have demolished half of one of those tins in one sitting",
   "created_utc": 1692754721,
   "score": 22,
   "submission_id": "15yn96i"
  },
  {
   "comment_id": "jxcw0ay",
   "message": "Oatmeal pies 😂 300 calories a pie is rough lol",
   "created_utc": 1692755809,
   "score": 21,
   "submission_id": "15yn96i"
  },
  {
   "comment_id": "jxcwcjz",
   "message": "Ben and Jerry’s, Cherry Garcia😋",
   "created_utc": 1692755961,
   "score": 22,
   "submission_id": "15yn96i"
  },
  {
   "comment_id": "jxcwfep",
   "message": "Cheese cake, homemade chocolate chip cookies or Oreos.",
   "created_utc": 1692755998,
   "score": 23,
   "submission_id": "15yn96i"
  },
  {
   "comment_id": "jxckwc7",
   "message": "Mr. Goodbars",
   "created_utc": 1692750939,
   "score": 18,
   "submission_id": "15yn96i"
  },
  {
   "comment_id": "jxcp1x7",
   "message": "Takis and Welch’s fruit snacks.",
   "created_utc": 1692752732,
   "score": 39,
   "submission_id": "15yn96i"
  },
  {
   "comment_id": "jxctq39",
   "message": "Chips and salsa",
   "created_utc": 1692754789,
   "score": 41,
   "submission_id": "15yn96i"
  },
  {
   "comment_id": "jxcgm5g",
   "message": "Dr Pepper.",
   "created_utc": 1692749100,
   "score": 118,
   "submission_id": "15yn96i"
  },
  {
   "comment_id": "jxcipx6",
   "message": "Nutella",
   "created_utc": 1692750009,
   "score": 77,
   "submission_id": "15yn96i"
  },
  {
   "comment_id": "jxctygu",
   "message": "Breakfast sandwiches, sausage egg and cheese.",
   "created_utc": 1692754891,
   "score": 17,
   "submission_id": "15yn96i"
  },
  {
   "comment_id": "jxcxl13",
   "message": "Gardettos",
   "created_utc": 1692756517,
   "score": 18,
   "submission_id": "15yn96i"
  },
  {
   "comment_id": "jxco4yo",
   "message": "Cocaine",
   "created_utc": 1692752334,
   "score": 110,
   "submission_id": "15yn96i"
  },
  {
   "comment_id": "jxcrpct",
   "message": "Weis brand Extreme Moose Tracks ice cream. It’s velvety chocolate ice cream with delicious fudge ripples and irresistible mini peanut butter cups mixed in.",
   "created_utc": 1692753894,
   "score": 16,
   "submission_id": "15yn96i"
  },
  {
   "comment_id": "jxd1gcl",
   "message": "Little Debbie Oatmeal creampies. Will eat a whole box in 1 sitting. lol",
   "created_utc": 1692758300,
   "score": 16,
   "submission_id": "15yn96i"
  },
  {
   "comment_id": "jxctpg5",
   "message": "Pizza rolls. Ive never not finished a bag in one sitting. Even the family size ones",
   "created_utc": 1692754781,
   "score": 16,
   "submission_id": "15yn96i"
  },
  {
   "comment_id": "jxcj1up",
   "message": "Peppermint Bark.",
   "created_utc": 1692750151,
   "score": 54,
   "submission_id": "15yn96i"
  },
  {
   "comment_id": "jxcixhf",
   "message": "Pork rinds. They will kill me. It's gonna be great",
   "created_utc": 1692750099,
   "score": 42,
   "submission_id": "15yn96i"
  },
  {
   "comment_id": "jxcsdlh",
   "message": "Fritos BBQ twists",
   "created_utc": 1692754191,
   "score": 14,
   "submission_id": "15yn96i"
  },
  {
   "comment_id": "jxcsu8v",
   "message": "Brownie brittle. \n\nIf you don’t know, just stay away. I’ve been known to mix the crumbs with milk and drink it.",
   "created_utc": 1692754397,
   "score": 13,
   "submission_id": "15yn96i"
  },
  {
   "comment_id": "jxcxnxd",
   "message": "Crunchy chee-tos. I'm half cheetah.",
   "created_utc": 1692756553,
   "score": 13,
   "submission_id": "15yn96i"
  },
  {
   "comment_id": "jxd1fs3",
   "message": "Cheddar Sunchips, can eat a whole bag in 5 minutes, things are unnecessarily delicious",
   "created_utc": 1692758292,
   "score": 14,
   "submission_id": "15yn96i"
  },
  {
   "comment_id": "jxcryri",
   "message": "Sour gummies or cherry Twizzlers",
   "created_utc": 1692754007,
   "score": 29,
   "submission_id": "15yn96i"
  },
  {
   "comment_id": "jxd2akv",
   "message": "Cadbury mini eggs. \n\nJust nope. I can look at a bowl and be totally fine. If I have one I will eat the entire bowl.",
   "created_utc": 1692758709,
   "score": 13,
   "submission_id": "15yn96i"
  },
  {
   "comment_id": "jxcq4d1",
   "message": "Microwave popcorn. 🍿",
   "created_utc": 1692753202,
   "score": 12,
   "submission_id": "15yn96i"
  },
  {
   "comment_id": "jxcsgjp",
   "message": "I guess heroin isn’t really food - although it was my preferred meal for a while - I’ll go with mothers frosted circus animal cookies.",
   "created_utc": 1692754227,
   "score": 12,
   "submission_id": "15yn96i"
  },
  {
   "comment_id": "jxcx004",
   "message": "Fresh mozzarella...",
   "created_utc": 1692756251,
   "score": 13,
   "submission_id": "15yn96i"
  },
  {
   "comment_id": "jxcyezm",
   "message": "Girl Scout cookies. I eat them as if they’re chips when I have them.",
   "created_utc": 1692756893,
   "score": 12,
   "submission_id": "15yn96i"
  },
  {
   "comment_id": "jxcyqd4",
   "message": "Krispy Kreme doughnuts",
   "created_utc": 1692757036,
   "score": 13,
   "submission_id": "15yn96i"
  },
  {
   "comment_id": "jxcrbrj",
   "message": "For me, watermelon and tajin. I end up eating the entire watermelon and getting sick.",
   "created_utc": 1692753727,
   "score": 23,
   "submission_id": "15yn96i"
  },
  {
   "comment_id": "jxct4dd",
   "message": "Really ripe pineapple. I eat it until my taste buds dissolve.",
   "created_utc": 1692754522,
   "score": 26,
   "submission_id": "15yn96i"
  },
  {
   "comment_id": "jxcjmdo",
   "message": "Potatoes and tomatoes have trace amounts of nicotine.",
   "created_utc": 1692750390,
   "score": 10,
   "submission_id": "15yn96i"
  },
  {
   "comment_id": "jxctp5q",
   "message": "Pretzels\n\nEspecially those long Old Dutch rods. Those with a jar of peanut butter will be the death of me.",
   "created_utc": 1692754777,
   "score": 11,
   "submission_id": "15yn96i"
  },
  {
   "comment_id": "jxd3jgx",
   "message": "Jerky",
   "created_utc": 1692759318,
   "score": 12,
   "submission_id": "15yn96i"
  },
  {
   "comment_id": "jxcigp5",
   "message": "Cheddar jalapeño Cheetos",
   "created_utc": 1692749901,
   "score": 32,
   "submission_id": "15yn96i"
  },
  {
   "comment_id": "jxcr5vz",
   "message": "Peanut Butter",
   "created_utc": 1692753657,
   "score": 10,
   "submission_id": "15yn96i"
  },
  {
   "comment_id": "jxcgrfs",
   "message": "Pasta carbonara (made by Italians)",
   "created_utc": 1692749162,
   "score": 20,
   "submission_id": "15yn96i"
  },
  {
   "comment_id": "jxchqr1",
   "message": "Lays potato chips.",
   "created_utc": 1692749588,
   "score": 21,
   "submission_id": "15yn96i"
  },
  {
   "comment_id": "jxcux5o",
   "message": "Hawaiian rolls. I can prob eat a whole 24 pack in one day if I really wanted to 😬 I’ve def eaten a 12 pack in a day 🫣",
   "created_utc": 1692755325,
   "score": 21,
   "submission_id": "15yn96i"
  },
  {
   "comment_id": "jxcqcua",
   "message": "Various types of chips, and Nerds. On more than one occasion, I have continued to pour Nerds into my mouth long past the point of nausea.",
   "created_utc": 1692753307,
   "score": 10,
   "submission_id": "15yn96i"
  },
  {
   "comment_id": "jxctlyp",
   "message": "Chips. \n\nAny type of chip.",
   "created_utc": 1692754738,
   "score": 9,
   "submission_id": "15yn96i"
  },
  {
   "comment_id": "jxctteh",
   "message": "Sticky Date Pudding. I can’t keep it in the house. I once gained 5kgs from eating it almost every night after dinner for a few weeks. It’s like crack to me. I will ruin my health if I have access to it.\n\nETA: all I had to do to lose the weight was simply stop eating the sticky date pudding. Proof that even just dropping one unhealthy thing from your diet can make you healthier (even if you don’t lose weight).",
   "created_utc": 1692754828,
   "score": 9,
   "submission_id": "15yn96i"
  },
  {
   "comment_id": "jxcwpsq",
   "message": "Those damn kettle corn pop corners",
   "created_utc": 1692756123,
   "score": 10,
   "submission_id": "15yn96i"
  },
  {
   "comment_id": "jxcz8p0",
   "message": "Whoppers. \n\nI'm turning that carton upside down. \n\nHonorable Mention: 🎖 Peanut Butter M\u0026amp;Ms",
   "created_utc": 1692757268,
   "score": 16,
   "submission_id": "15yn96i"
  },
  {
   "comment_id": "jxcx2ew",
   "message": "Cheesecake",
   "created_utc": 1692756281,
   "score": 9,
   "submission_id": "15yn96i"
  },
  {
   "comment_id": "jxczwaw",
   "message": "Redvines.  They come in this enormous tub.  They disappear from that tub way too fast.",
   "created_utc": 1692757565,
   "score": 8,
   "submission_id": "15yn96i"
  },
  {
   "comment_id": "jxd08a9",
   "message": "Chili cheese Fritos",
   "created_utc": 1692757720,
   "score": 8,
   "submission_id": "15yn96i"
  },
  {
   "comment_id": "jxd3n1v",
   "message": "I have 2... cashews. They're so addicting, I just can't stop. I'm also a sucker for most things coconut, so the Outshine fruit bars brand of creamy coconut popsicles.",
   "created_utc": 1692759368,
   "score": 7,
   "submission_id": "15yn96i"
  },
  {
   "comment_id": "jxcugln",
   "message": "Little Debbie snack cakes",
   "created_utc": 1692755119,
   "score": 6,
   "submission_id": "15yn96i"
  },
  {
   "comment_id": "jxcy5sk",
   "message": "Tim Tams",
   "created_utc": 1692756779,
   "score": 7,
   "submission_id": "15yn96i"
  },
  {
   "comment_id": "jxd3gc8",
   "message": "Bacon",
   "created_utc": 1692759276,
   "score": 7,
   "submission_id": "15yn96i"
  },
  {
   "comment_id": "jxcj3mi",
   "message": "*Anything* with chocolate.  I just don't keep it around.",
   "created_utc": 1692750172,
   "score": 5,
   "submission_id": "15yn96i"
  },
  {
   "comment_id": "jxcm7sy",
   "message": "Those marshmallow bananas. I don't know what it is but I can only eat them a bag at a time",
   "created_utc": 1692751508,
   "score": 6,
   "submission_id": "15yn96i"
  },
  {
   "comment_id": "jxcqonw",
   "message": "Pork rinds",
   "created_utc": 1692753449,
   "score": 5,
   "submission_id": "15yn96i"
  },
  {
   "comment_id": "jxctki0",
   "message": "Peanut butter— creamy, chunky, extra chunky.  I have zero willpower.",
   "created_utc": 1692754721,
   "score": 6,
   "submission_id": "15yn96i"
  },
  {
   "comment_id": "jxcvdo9",
   "message": "Well...cheese is more addictive than cocaine...yet I have plenty of cheese at home.",
   "created_utc": 1692755530,
   "score": 6,
   "submission_id": "15yn96i"
  },
  {
   "comment_id": "jxcvjuw",
   "message": "Mentos... I once eat 3 packs a day (I was in a bad year)",
   "created_utc": 1692755605,
   "score": 6,
   "submission_id": "15yn96i"
  },
  {
   "comment_id": "jxcyzoi",
   "message": "Cheese doodles by Wise.  Can't find them here anymore and they cost to much on Amazon.   But oh, they are so good I could eat the entire bag in one sitting.  Cheetos has nothing on them.",
   "created_utc": 1692757155,
   "score": 5,
   "submission_id": "15yn96i"
  },
  {
   "comment_id": "jxd3cdj",
   "message": "Gummies (bears, worms, fruit snacks, anything.) They are soon bad for my TMJ.\n\nAlso, chocolate covered pretzels and espresso beans. My dad would buy me a big carton of each when he would visit me at college. I quickly learned that if I didn't hide them from myself, they would be gone in one night. These were like 3 pound cartons.",
   "created_utc": 1692759222,
   "score": 5,
   "submission_id": "15yn96i"
  },
  {
   "comment_id": "jxclpwl",
   "message": "Cocaine brownies",
   "created_utc": 1692751294,
   "score": 6,
   "submission_id": "15yn96i"
  },
  {
   "comment_id": "jxcma8e",
   "message": "Purdy's sea salt chocolate caramel squares.",
   "created_utc": 1692751536,
   "score": 5,
   "submission_id": "15yn96i"
  },
  {
   "comment_id": "jxcrgvp",
   "message": "Dip",
   "created_utc": 1692753789,
   "score": 5,
   "submission_id": "15yn96i"
  },
  {
   "comment_id": "jxcuhii",
   "message": "Blue organic corn chips, 1st almost any other corn chips 2nd.",
   "created_utc": 1692755130,
   "score": 5,
   "submission_id": "15yn96i"
  },
  {
   "comment_id": "jxcw1gh",
   "message": "Peanut butter. \n\nHigh calorie consintration of fat and sugar that you can eat with more carbs in a pbj or by the spoonful.",
   "created_utc": 1692755824,
   "score": 5,
   "submission_id": "15yn96i"
  },
  {
   "comment_id": "jxcwzi2",
   "message": "Soy sauce. I could honestly down a bottle if it wouldn’t literally kill me",
   "created_utc": 1692756245,
   "score": 5,
   "submission_id": "15yn96i"
  },
  {
   "comment_id": "jxcxf5z",
   "message": "Brie",
   "created_utc": 1692756443,
   "score": 5,
   "submission_id": "15yn96i"
  },
  {
   "comment_id": "jxcyonz",
   "message": "",
   "created_utc": 0,
   "score": 0,
   "submission_id": "15yn96i"
  }
 ]
}